{
    "addr": "0x47d47c1f174bf9e7322974998e62968cec96257c",
    "addr_orig": true,
    "bytecode": [
        "bytecode/main.hex"
    ],
    "bytecode_orig": false,
    "chain": "main",
    "chain_orig": true,
    "classifications": [
        [
            "Unchecked External Call",
            false
        ],
        [
            "Dos Under external influence",
            false
        ],
        [
            "strict balance equality",
            false
        ],
        [
            "Unmatched type assignment",
            false
        ],
        [
            "Transaction state Dependency",
            false
        ],
        [
            "Reentrancy",
            false
        ],
        [
            "Hard Code Address",
            false
        ],
        [
            "Block Info Dependency",
            true
        ],
        [
            "Nest Call",
            false
        ],
        [
            "Deprecated APIs",
            false
        ],
        [
            "Compiler Version not fixed",
            true
        ],
        [
            "Misleading Data Location",
            false
        ],
        [
            "Unused statement",
            false
        ],
        [
            "Unmatched ERC-20 standard",
            false
        ],
        [
            "Missing Return statement",
            false
        ],
        [
            "Missing Interrupter",
            true
        ],
        [
            "Missing Reminder",
            false
        ],
        [
            "Greedy Contract",
            false
        ],
        [
            "High Gas Consumption Function Type",
            true
        ],
        [
            "High Gas Consumption Data Type",
            false
        ]
    ],
    "compiler": "v0.4.19+commit.c4cbbb05",
    "compiler_orig": false,
    "contractname": "MineBlocks",
    "contractname_orig": false,
    "dataset": "CodeSmells",
    "etc": {},
    "fp_bytecode": "edce305ba7307475fcc13c404cb70d8a",
    "fp_runtime": "0870ad4d26ab7d93344647a83af76d5b",
    "fp_sol": "9ed531b1659bee273bc498bddee7f974",
    "fp_sol2": "edd78b8b8d0c3793b7656f95082bf470",
    "id": "0x47d47c1f174bf9e7322974998e62968cec96257c",
    "info": [],
    "runtime": [
        "runtime/main.rt.hex"
    ],
    "runtime_orig": false,
    "sol": [
        "source/etherscan.sol"
    ],
    "sol_orig": false
}