{
    "addr": "0x8c5344637d2b14d1c2b340fe0a118580738198fb",
    "addr_orig": true,
    "bytecode": [
        "bytecode/main.hex"
    ],
    "bytecode_orig": false,
    "chain": "main",
    "chain_orig": false,
    "classifications": [
        [
            "airdrop-hunting",
            true
        ]
    ],
    "compiler": "v0.4.25+commit.59dbf8f1",
    "compiler_orig": false,
    "contractname": "Seeflast",
    "contractname_orig": false,
    "dataset": "EverEvolvingG",
    "etc": {},
    "fp_bytecode": "18e93ff1980a0c356f0a0c32e2784eab",
    "fp_runtime": "b220e5576fd8b3ef4dd573b0fd01b062",
    "fp_sol": "33b166953612719d9e050d6f344517bb",
    "fp_sol2": "1a0e7c491fc5144f3cf2866e1b244a45",
    "id": "0x8c5344637d2b14d1c2b340fe0a118580738198fb",
    "info": [],
    "runtime": [
        "runtime/main.rt.hex"
    ],
    "runtime_orig": false,
    "sol": [
        "source/etherscan.sol"
    ],
    "sol_orig": false
}