{
    "addr": "0x22cdaa7b4460a046f0cc9878a4f79fdc2f187316",
    "addr_orig": true,
    "bytecode": [
        "bytecode/main.hex"
    ],
    "bytecode_orig": false,
    "chain": "main",
    "chain_orig": false,
    "classifications": [
        [
            "EO offchain",
            true
        ]
    ],
    "compiler": "v0.4.10+commit.f0d539ae",
    "compiler_orig": false,
    "contractname": "Etheroll",
    "contractname_orig": false,
    "dataset": "EthRacer",
    "etc": {},
    "fp_bytecode": "b7bc38d0120ba84a4702ed9aa5097251",
    "fp_runtime": "3b66001255f8589cb10b581bf3550e1a",
    "fp_sol": "c5b20adb445f9ca6d967766d3ff41612",
    "fp_sol2": "87156d9ef94ee195c8acfd089885e3f7",
    "id": "0x22cdaa7b4460a046f0cc9878a4f79fdc2f187316",
    "info": [],
    "runtime": [
        "runtime/main.rt.hex"
    ],
    "runtime_orig": false,
    "sol": [
        "source/etherscan.sol"
    ],
    "sol_orig": false
}