{
    "addr": "0x7776a879ab315314db00f193a85aee7c53def11d",
    "addr_orig": true,
    "bytecode": [
        "bytecode/main.hex"
    ],
    "bytecode_orig": false,
    "chain": "main",
    "chain_orig": false,
    "classifications": [
        [
            "lowlevelcall_result",
            true
        ]
    ],
    "compiler": "v0.4.22-nightly.2018.3.8+commit.fbc29f6d",
    "compiler_orig": false,
    "contractname": "ETHERCREDIT",
    "contractname_orig": true,
    "dataset": "Doublade",
    "etc": {},
    "fp_bytecode": "218cc64eeea73061f0b5715696c846b5",
    "fp_runtime": "14443628757ef762ac085d095c83c99d",
    "fp_sol": "b69969618da401e7416b9da9a350b963",
    "fp_sol2": "2d176e92eee45d38f43211ed40b8c3bc",
    "id": "0x7776a879ab315314db00f193a85aee7c53def11d-ETHERCREDIT-lowlevelcall_result",
    "info": [],
    "runtime": [
        "runtime/main.rt.hex"
    ],
    "runtime_orig": false,
    "sol": [
        "source/1_test1867.sol",
        "source/2_etherscan.sol"
    ],
    "sol_orig": true
}