{
    "addr": null,
    "addr_orig": null,
    "bytecode": [
        "bytecode/bytecode.hex"
    ],
    "bytecode_orig": true,
    "chain": null,
    "chain_orig": null,
    "classifications": [
        [
            "Improper use of assert",
            true
        ]
    ],
    "compiler": null,
    "compiler_orig": null,
    "contractname": "GasModel",
    "contractname_orig": false,
    "dataset": "JiuZhou",
    "etc": {},
    "fp_bytecode": "b0035007c29e38d8d8dff0cf027a160a",
    "fp_runtime": "9ee2e7d1185c475e4fd069a1bbad1f82",
    "fp_sol": "bfde15c487502cceddb4c4778e3e6ec7",
    "fp_sol2": "6151fa4f10853eeb7866b147d5c7e566",
    "id": "AssertError",
    "info": [
        "info/readme.md"
    ],
    "runtime": [
        "runtime/computed.rt.hex"
    ],
    "runtime_orig": false,
    "sol": [
        "source/AssertError.sol"
    ],
    "sol_orig": true
}