{
    "addr": "0x7a8bbfcccb6b80579d5965aa8d4a4b2294ac166e",
    "addr_orig": true,
    "bytecode": [
        "bytecode/main.hex"
    ],
    "bytecode_orig": false,
    "chain": "main",
    "chain_orig": true,
    "classifications": [
        [
            "Unchecked External Call",
            false
        ],
        [
            "Dos Under external influence",
            false
        ],
        [
            "strict balance equality",
            false
        ],
        [
            "Unmatched type assignment",
            false
        ],
        [
            "Transaction state Dependency",
            false
        ],
        [
            "Reentrancy",
            false
        ],
        [
            "Hard Code Address",
            false
        ],
        [
            "Block Info Dependency",
            false
        ],
        [
            "Nest Call",
            false
        ],
        [
            "Deprecated APIs",
            false
        ],
        [
            "Compiler Version not fixed",
            true
        ],
        [
            "Misleading Data Location",
            false
        ],
        [
            "Unused statement",
            false
        ],
        [
            "Unmatched ERC-20 standard",
            true
        ],
        [
            "Missing Return statement",
            false
        ],
        [
            "Missing Interrupter",
            true
        ],
        [
            "Missing Reminder",
            false
        ],
        [
            "Greedy Contract",
            false
        ],
        [
            "High Gas Consumption Function Type",
            true
        ],
        [
            "High Gas Consumption Data Type",
            false
        ]
    ],
    "compiler": "v0.4.20+commit.3155dd80",
    "compiler_orig": false,
    "contractname": "mkethToken",
    "contractname_orig": false,
    "dataset": "CodeSmells",
    "etc": {},
    "fp_bytecode": "5ac076ce71fa797d0c4e065e7010c8ba",
    "fp_runtime": "87955a5cc7fad1891bddaa4d2de408e3",
    "fp_sol": "79792891790db94c2f58a87aa65ff958",
    "fp_sol2": "4780954aa383b18bfccf02a35f7a7296",
    "id": "0x7a8bbfcccb6b80579d5965aa8d4a4b2294ac166e",
    "info": [],
    "runtime": [
        "runtime/main.rt.hex"
    ],
    "runtime_orig": false,
    "sol": [
        "source/etherscan.sol"
    ],
    "sol_orig": false
}