{
    "addr": null,
    "addr_orig": false,
    "bytecode": [],
    "bytecode_orig": null,
    "chain": null,
    "chain_orig": null,
    "classifications": [
        [
            "selfdestruct_result",
            false
        ]
    ],
    "compiler": "v0.4.25+commit.59dbf8f1",
    "compiler_orig": false,
    "contractname": "TokenBase",
    "contractname_orig": true,
    "dataset": "Doublade",
    "etc": {
        "same address, different source": [
            [
                "0x07a5410e4d3ef9680137e0242ccdb78425cb6c43",
                "main"
            ]
        ],
        "verified source": [
            "0x07a5410e4d3ef9680137e0242ccdb78425cb6c43",
            "main",
            "ShinHoDeung"
        ]
    },
    "fp_bytecode": null,
    "fp_runtime": null,
    "fp_sol": "94211808f42e159952c0cad04f38e637",
    "fp_sol2": "eb4f864224b9a9585cdfb3c927d41eea",
    "id": "0x07a5410e4d3ef9680137e0242ccdb78425cb6c43-TokenBase-selfdestruct_result",
    "info": [],
    "runtime": [],
    "runtime_orig": null,
    "sol": [
        "source/1_test116.sol",
        "source/2_etherscan.sol"
    ],
    "sol_orig": true
}