{
    "addr": null,
    "addr_orig": null,
    "bytecode": [],
    "bytecode_orig": null,
    "chain": null,
    "chain_orig": null,
    "classifications": [
        [
            "Timestamp-Dependency",
            true
        ]
    ],
    "compiler": null,
    "compiler_orig": null,
    "contractname": "TAMCContract",
    "contractname_orig": false,
    "dataset": "SolidiFI",
    "etc": {},
    "fp_bytecode": null,
    "fp_runtime": null,
    "fp_sol": "4190feb5d4ce14bf8539d05bb5082aee",
    "fp_sol2": "c18d92d36526397d819ac35f8cc723d8",
    "id": "Timestamp-Dependency-39",
    "info": [
        "info/BugLog_39.csv"
    ],
    "runtime": [],
    "runtime_orig": null,
    "sol": [
        "source/buggy_39.sol"
    ],
    "sol_orig": true
}