{
    "addr": "0x6fc1ee575e9023aea1c45b4dfc9acf603ea9f63f",
    "addr_orig": true,
    "bytecode": [
        "bytecode/main.hex"
    ],
    "bytecode_orig": false,
    "chain": "main",
    "chain_orig": false,
    "classifications": [
        [
            "honeypot",
            true
        ]
    ],
    "compiler": "v0.4.24+commit.e67f0147",
    "compiler_orig": false,
    "contractname": "MultiFundsWallet",
    "contractname_orig": false,
    "dataset": "EverEvolvingG",
    "etc": {},
    "fp_bytecode": "92897c15f12ba521a94260972d5976d6",
    "fp_runtime": "aeab002d37b9b628e1a9a71f7190a391",
    "fp_sol": "1fc0814aefdbd2d59b12e463f24d481d",
    "fp_sol2": "588dbbf7afe84cbc4816779dadbe131a",
    "id": "0x6fc1ee575e9023aea1c45b4dfc9acf603ea9f63f",
    "info": [],
    "runtime": [
        "runtime/main.rt.hex"
    ],
    "runtime_orig": false,
    "sol": [
        "source/etherscan.sol"
    ],
    "sol_orig": false
}