{"status": "1", "message": "OK", "result": [{"SourceCode": "pragma solidity ^0.4.13;\r\ncontract Token {\r\n    \r\n\t/* Public variables of the token */\r\n\tstring public name;\r\n\tstring public symbol;\r\n\tuint8 public decimals;\r\n\tuint256 public totalSupply;\r\n    \r\n\t/* This creates an array with all balances */\r\n\tmapping (address => uint256) public balanceOf;\r\n\r\n\t/* This generates a public event on the blockchain that will notify clients */\r\n\tevent Transfer(address indexed from, address indexed to, uint256 value);\r\n\r\n\tfunction Token() {\r\n\t    totalSupply = 100*(10**8)*(10**18);\r\n\t\tbalanceOf[msg.sender] = 100*(10**8)*(10**18);              // Give the creator all initial tokens\r\n\t\tname = \"Token of ENT\";                                   // Set the name for display purposes\r\n\t\tsymbol = \"TOE\";                               // Set the symbol for display purposes\r\n\t\tdecimals = 18;                            // Amount of decimals for display purposes\r\n\t}\r\n\r\n\tfunction transfer(address _to, uint256 _value) {\r\n\t/* Check if sender has balance and for overflows */\r\n\tif (balanceOf[msg.sender] < _value || balanceOf[_to] + _value < balanceOf[_to])\r\n\t\trevert();\r\n\t/* Add and subtract new balances */\r\n\tbalanceOf[msg.sender] -= _value;\r\n\tbalanceOf[_to] += _value;\r\n\t/* Notifiy anyone listening that this transfer took place */\r\n\tTransfer(msg.sender, _to, _value);\r\n\t}\r\n\r\n\t/* This unnamed function is called whenever someone tries to send ether to it */\r\n\tfunction () {\r\n\trevert();     // Prevents accidental sending of ether\r\n\t}\r\n}", "ABI": "[{\"constant\":true,\"inputs\":[],\"name\":\"name\",\"outputs\":[{\"name\":\"\",\"type\":\"string\"}],\"payable\":false,\"type\":\"function\"},{\"constant\":true,\"inputs\":[],\"name\":\"totalSupply\",\"outputs\":[{\"name\":\"\",\"type\":\"uint256\"}],\"payable\":false,\"type\":\"function\"},{\"constant\":true,\"inputs\":[],\"name\":\"decimals\",\"outputs\":[{\"name\":\"\",\"type\":\"uint8\"}],\"payable\":false,\"type\":\"function\"},{\"constant\":true,\"inputs\":[{\"name\":\"\",\"type\":\"address\"}],\"name\":\"balanceOf\",\"outputs\":[{\"name\":\"\",\"type\":\"uint256\"}],\"payable\":false,\"type\":\"function\"},{\"constant\":true,\"inputs\":[],\"name\":\"symbol\",\"outputs\":[{\"name\":\"\",\"type\":\"string\"}],\"payable\":false,\"type\":\"function\"},{\"constant\":false,\"inputs\":[{\"name\":\"_to\",\"type\":\"address\"},{\"name\":\"_value\",\"type\":\"uint256\"}],\"name\":\"transfer\",\"outputs\":[],\"payable\":false,\"type\":\"function\"},{\"inputs\":[],\"payable\":false,\"type\":\"constructor\"},{\"payable\":false,\"type\":\"fallback\"},{\"anonymous\":false,\"inputs\":[{\"indexed\":true,\"name\":\"from\",\"type\":\"address\"},{\"indexed\":true,\"name\":\"to\",\"type\":\"address\"},{\"indexed\":false,\"name\":\"value\",\"type\":\"uint256\"}],\"name\":\"Transfer\",\"type\":\"event\"}]", "ContractName": "Token", "CompilerVersion": "v0.4.13+commit.fb4cb1a", "OptimizationUsed": "0", "Runs": "200", "ConstructorArguments": "", "Library": "", "SwarmSource": "bzzr://d09e3780378a5eab99c9bda64ec4686df7bcac1a24d09290f88e466e9c857678"}]}