{"status": "1", "message": "OK", "result": [{"SourceCode": "pragma solidity ^0.4.4;\r\n\r\n\r\n// ERC20 token interface is implemented only partially.\r\n// Token transfer is prohibited due to spec (see PRESALE-SPEC.md),\r\n// hence some functions are left undefined:\r\n//  - transfer, transferFrom,\r\n//  - approve, allowance.\r\n\r\ncontract PresaleToken {\r\n\r\n    /// @dev Constructor\r\n    /// @param _tokenManager Token manager address.\r\n    function PresaleToken(address _tokenManager) {\r\n        tokenManager = _tokenManager;\r\n    }\r\n\r\n\r\n    /*/\r\n     *  Constants\r\n    /*/\r\n\r\n    string public name = \"SONM Presale Token\";\r\n    string public symbol = \"SPT\";\r\n    uint   public decimals = 18;\r\n\r\n    uint public PRICE = 200; // 200 SPT per Ether\r\n\r\n    // 50 000 eth * 200 price\r\n    uint public TOKEN_SUPPLY_LIMIT = 10000000 * (1 ether / 1 wei);\r\n\r\n\r\n\r\n    /*/\r\n     *  Token state\r\n    /*/\r\n\r\n    enum Phase {\r\n        Created,\r\n        Running,\r\n        Paused,\r\n        Migrating,\r\n        Migrated\r\n    }\r\n\r\n    Phase public currentPhase = Phase.Created;\r\n    uint public totalSupply = 0; // amount of tokens already sold\r\n\r\n    // Token manager has exclusive priveleges to call administrative\r\n    // functions on this contract.\r\n    address public tokenManager;\r\n    // Crowdsale manager has exclusive priveleges to burn presale tokens.\r\n    address public crowdsaleManager;\r\n\r\n    mapping (address => uint256) private balance;\r\n\r\n\r\n    modifier onlyTokenManager()     { if(msg.sender != tokenManager) throw; _; }\r\n    modifier onlyCrowdsaleManager() { if(msg.sender != crowdsaleManager) throw; _; }\r\n\r\n\r\n    /*/\r\n     *  Events\r\n    /*/\r\n\r\n    event LogBuy(address indexed owner, uint value);\r\n    event LogBurn(address indexed owner, uint value);\r\n    event LogPhaseSwitch(Phase newPhase);\r\n\r\n\r\n    /*/\r\n     *  Public functions\r\n    /*/\r\n\r\n    function() payable {\r\n        buyTokens(msg.sender);\r\n    }\r\n\r\n    /// @dev Lets buy you some tokens.\r\n    function buyTokens(address _buyer) public payable {\r\n        // Available only if presale is running.\r\n        if(currentPhase != Phase.Running) throw;\r\n\r\n        if(msg.value == 0) throw;\r\n        uint newTokens = msg.value * PRICE;\r\n        if (totalSupply + newTokens > TOKEN_SUPPLY_LIMIT) throw;\r\n        balance[_buyer] += newTokens;\r\n        totalSupply += newTokens;\r\n        LogBuy(_buyer, newTokens);\r\n    }\r\n\r\n\r\n    /// @dev Returns number of tokens owned by given address.\r\n    /// @param _owner Address of token owner.\r\n    function burnTokens(address _owner) public\r\n        onlyCrowdsaleManager\r\n    {\r\n        // Available only during migration phase\r\n        if(currentPhase != Phase.Migrating) throw;\r\n\r\n        uint tokens = balance[_owner];\r\n        if(tokens == 0) throw;\r\n        balance[_owner] = 0;\r\n        totalSupply -= tokens;\r\n        LogBurn(_owner, tokens);\r\n\r\n        // Automatically switch phase when migration is done.\r\n        if(totalSupply == 0) {\r\n            currentPhase = Phase.Migrated;\r\n            LogPhaseSwitch(Phase.Migrated);\r\n        }\r\n    }\r\n\r\n\r\n    /// @dev Returns number of tokens owned by given address.\r\n    /// @param _owner Address of token owner.\r\n    function balanceOf(address _owner) constant returns (uint256) {\r\n        return balance[_owner];\r\n    }\r\n\r\n\r\n    /*/\r\n     *  Administrative functions\r\n    /*/\r\n\r\n    function setPresalePhase(Phase _nextPhase) public\r\n        onlyTokenManager\r\n    {\r\n        bool canSwitchPhase\r\n            =  (currentPhase == Phase.Created && _nextPhase == Phase.Running)\r\n            || (currentPhase == Phase.Running && _nextPhase == Phase.Paused)\r\n                // switch to migration phase only if crowdsale manager is set\r\n            || ((currentPhase == Phase.Running || currentPhase == Phase.Paused)\r\n                && _nextPhase == Phase.Migrating\r\n                && crowdsaleManager != 0x0)\r\n            || (currentPhase == Phase.Paused && _nextPhase == Phase.Running)\r\n                // switch to migrated only if everyting is migrated\r\n            || (currentPhase == Phase.Migrating && _nextPhase == Phase.Migrated\r\n                && totalSupply == 0);\r\n\r\n        if(!canSwitchPhase) throw;\r\n        currentPhase = _nextPhase;\r\n        LogPhaseSwitch(_nextPhase);\r\n    }\r\n\r\n\r\n    function withdrawEther() public\r\n        onlyTokenManager\r\n    {\r\n        // Available at any phase.\r\n        if(this.balance > 0) {\r\n            if(!tokenManager.send(this.balance)) throw;\r\n        }\r\n    }\r\n\r\n\r\n    function setCrowdsaleManager(address _mgr) public\r\n        onlyTokenManager\r\n    {\r\n        // You can't change crowdsale contract when migration is in progress.\r\n        if(currentPhase == Phase.Migrating) throw;\r\n        crowdsaleManager = _mgr;\r\n    }\r\n}", "ABI": "[{\"constant\":true,\"inputs\":[],\"name\":\"currentPhase\",\"outputs\":[{\"name\":\"\",\"type\":\"uint8\"}],\"payable\":false,\"type\":\"function\"},{\"constant\":true,\"inputs\":[],\"name\":\"name\",\"outputs\":[{\"name\":\"\",\"type\":\"string\"}],\"payable\":false,\"type\":\"function\"},{\"constant\":true,\"inputs\":[],\"name\":\"totalSupply\",\"outputs\":[{\"name\":\"\",\"type\":\"uint256\"}],\"payable\":false,\"type\":\"function\"},{\"constant\":false,\"inputs\":[{\"name\":\"_nextPhase\",\"type\":\"uint8\"}],\"name\":\"setPresalePhase\",\"outputs\":[],\"payable\":false,\"type\":\"function\"},{\"constant\":true,\"inputs\":[],\"name\":\"TOKEN_SUPPLY_LIMIT\",\"outputs\":[{\"name\":\"\",\"type\":\"uint256\"}],\"payable\":false,\"type\":\"function\"},{\"constant\":true,\"inputs\":[],\"name\":\"tokenManager\",\"outputs\":[{\"name\":\"\",\"type\":\"address\"}],\"payable\":false,\"type\":\"function\"},{\"constant\":true,\"inputs\":[],\"name\":\"decimals\",\"outputs\":[{\"name\":\"\",\"type\":\"uint256\"}],\"payable\":false,\"type\":\"function\"},{\"constant\":true,\"inputs\":[],\"name\":\"crowdsaleManager\",\"outputs\":[{\"name\":\"\",\"type\":\"address\"}],\"payable\":false,\"type\":\"function\"},{\"constant\":false,\"inputs\":[{\"name\":\"_mgr\",\"type\":\"address\"}],\"name\":\"setCrowdsaleManager\",\"outputs\":[],\"payable\":false,\"type\":\"function\"},{\"constant\":true,\"inputs\":[{\"name\":\"_owner\",\"type\":\"address\"}],\"name\":\"balanceOf\",\"outputs\":[{\"name\":\"\",\"type\":\"uint256\"}],\"payable\":false,\"type\":\"function\"},{\"constant\":false,\"inputs\":[],\"name\":\"withdrawEther\",\"outputs\":[],\"payable\":false,\"type\":\"function\"},{\"constant\":true,\"inputs\":[],\"name\":\"PRICE\",\"outputs\":[{\"name\":\"\",\"type\":\"uint256\"}],\"payable\":false,\"type\":\"function\"},{\"constant\":true,\"inputs\":[],\"name\":\"symbol\",\"outputs\":[{\"name\":\"\",\"type\":\"string\"}],\"payable\":false,\"type\":\"function\"},{\"constant\":false,\"inputs\":[{\"name\":\"_owner\",\"type\":\"address\"}],\"name\":\"burnTokens\",\"outputs\":[],\"payable\":false,\"type\":\"function\"},{\"constant\":false,\"inputs\":[{\"name\":\"_buyer\",\"type\":\"address\"}],\"name\":\"buyTokens\",\"outputs\":[],\"payable\":true,\"type\":\"function\"},{\"inputs\":[{\"name\":\"_tokenManager\",\"type\":\"address\"}],\"payable\":false,\"type\":\"constructor\"},{\"payable\":true,\"type\":\"fallback\"},{\"anonymous\":false,\"inputs\":[{\"indexed\":true,\"name\":\"owner\",\"type\":\"address\"},{\"indexed\":false,\"name\":\"value\",\"type\":\"uint256\"}],\"name\":\"LogBuy\",\"type\":\"event\"},{\"anonymous\":false,\"inputs\":[{\"indexed\":true,\"name\":\"owner\",\"type\":\"address\"},{\"indexed\":false,\"name\":\"value\",\"type\":\"uint256\"}],\"name\":\"LogBurn\",\"type\":\"event\"},{\"anonymous\":false,\"inputs\":[{\"indexed\":false,\"name\":\"newPhase\",\"type\":\"uint8\"}],\"name\":\"LogPhaseSwitch\",\"type\":\"event\"}]", "ContractName": "PresaleToken", "CompilerVersion": "v0.4.8+commit.60cc1668", "OptimizationUsed": "1", "Runs": "200", "ConstructorArguments": "000000000000000000000000e51fc42848679fb21b7adfea4d5162b4f6fd3878", "EVMVersion": "Default", "Library": "", "LicenseType": "", "Proxy": "0", "Implementation": "", "SwarmSource": "bzzr://02a558fe8abcae2982d5d6660ea80f9f24c752f6a7b9781c8ed54e49b1051be1"}]}